Workbook

Sheet Methodology Overview
A1: THE Interdisciplinary Rankings — Inputs Pillar (19%) → Industry Funding (11%)
A2: Measures Industry Financial Engagement in Cross-Disciplinary University Research | 11% of Total Ranking
A4: # | B4: Sub-Indicator | C4: Description & Measurement | D4: Approx. Weight
A5: 1 | B5: Industry-Sponsored Research Income (Normalized) | C5: Total research funding received from industry partners, normalized by academic staff (FTE). Includes contract research, sponsored projects, co-funded R&D, industry CSR-funded research, and technology development agreements. PPP-adjusted for global comparability. Signals the institution's relevance to industry R&D needs. | D5: ~4%
A6: 2 | B6: Cross-Disciplinary Industry Funding | C6: Proportion of industry research income explicitly directed to projects spanning 2+ departments or ASJC areas. Includes co-funded joint labs, industry chairs covering multiple disciplines, and multi-domain sponsored projects. Captures industry's investment in convergent science capabilities. | D6: ~2.5%
A7: 3 | B7: Industry Partner Diversity | C7: Count and diversity of unique industry partners funding research. Shannon entropy on sector distribution (IT, pharma, automotive, energy, FMCG, defence, agri, etc.). More diverse industry partner portfolio = stronger knowledge exchange capacity. | D7: ~1.5%
A8: 4 | B8: Joint R&D Centres, Chairs & Co-Funded Labs | C8: Count and quality of formally established industry-co-funded research infrastructure: joint R&D centres, endowed/sponsored chairs, co-funded laboratories, and industry Centres of Excellence (CoEs). Assessed via active status, output, and disciplines integrated. | D8: ~1.5%
A9: 5 | B9: Industry Funding Sustainability & Pipeline | C9: Multi-year industry funding trajectory: CAGR over 5 years, proportion of multi-year agreements (vs. one-off grants), and pipeline value of signed but un-disbursed industry commitments. Measures stability and growth of industry R&D relationship. | D9: ~1%
A10: 6 | B10: Industry Consultancy & Service Income | C10: Revenue from consultancy, testing, certification, and technical services provided to industry using multi-domain expertise. Separated from sponsored research but signals applied knowledge relevance. Normalized by FTE. | D10: ~0.5%
A12: Key Reference Notes
A13: • Industry Funding contributes 11% to total ranking — the second sub-component of the Inputs pillar (19%), alongside Research Funding (8%).
A14: • Together, Inputs pillar = Research Funding (8%) + Industry Funding (11%) = 19% of total Interdisciplinary Science Ranking.
A15: • Data sources: institutional finance records, MoU/agreement databases, TTO records, audited accounts, THE submission.
A16: • Normalization by academic FTE ensures fair comparison between large and small institutions.
A17: • Cross-disciplinary industry funding identified by project scope spanning 2+ departments/ASJC areas in signed agreements.
A18: • Industry partner diversity uses Shannon entropy: H = −Σ pᵢ × log₂(pᵢ) on proportions across industry sector categories.
A19: • Consultancy income is separated from sponsored research; both are important but serve different analytical purposes.
A20: • PPP-adjusted figures used for global comparability; currency conversion uses World Bank PPP rates.

Sheet 1. Industry Research Income
A1: Industry-Sponsored Research Income (5-Year Window)
A2: Total industry R&D funding | Normalized by academic FTE | PPP-adjusted for global comparability
A3: S.No. | B3: University Name | C3: Country | D3: Year 1 (INR Cr / USD M) | E3: Year 2 | F3: Year 3 | G3: Year 4 | H3: Year 5 | I3: 5-Year Total | J3: Academic Staff (FTE) | K3: Industry Income per FTE | L3: Reporting Period
A4: 1 | I4: =SUM(D4:H4) -> 0 | K4: =IF(J4>0,I4/J4,0) -> 0
A5: 2 | I5: =SUM(D5:H5) -> 0 | K5: =IF(J5>0,I5/J5,0) -> 0
A6: 3 | I6: =SUM(D6:H6) -> 0 | K6: =IF(J6>0,I6/J6,0) -> 0
A7: 4 | I7: =SUM(D7:H7) -> 0 | K7: =IF(J7>0,I7/J7,0) -> 0
A8: 5 | I8: =SUM(D8:H8) -> 0 | K8: =IF(J8>0,I8/J8,0) -> 0
A9: 6 | I9: =SUM(D9:H9) -> 0 | K9: =IF(J9>0,I9/J9,0) -> 0
A10: 7 | I10: =SUM(D10:H10) -> 0 | K10: =IF(J10>0,I10/J10,0) -> 0
A11: 8 | I11: =SUM(D11:H11) -> 0 | K11: =IF(J11>0,I11/J11,0) -> 0
A12: 9 | I12: =SUM(D12:H12) -> 0 | K12: =IF(J12>0,I12/J12,0) -> 0
A13: 10 | I13: =SUM(D13:H13) -> 0 | K13: =IF(J13>0,I13/J13,0) -> 0
A14: 11 | I14: =SUM(D14:H14) -> 0 | K14: =IF(J14>0,I14/J14,0) -> 0
A15: 12 | I15: =SUM(D15:H15) -> 0 | K15: =IF(J15>0,I15/J15,0) -> 0
... A33: 30 | I33: =SUM(D33:H33) -> 0 | K33: =IF(J33>0,I33/J33,0) -> 0
A35: Summary Statistics
A36: Total Industry Funding (All Universities) | F36: =SUM(I4:I33) -> 0
A37: Average Industry Income per FTE | F37: =IF(COUNTA(K4:K33)>0,AVERAGE(K4:K33),0) -> 0
A38: Highest Industry Income per FTE | F38: =MAX(K4:K33) -> 0
A39: Median Industry Income per FTE | F39: =MEDIAN(K4:K33) -> 0

Sheet 2. Funding by Sector
A1: Industry Research Funding by Sector (5-Year Aggregate)
A2: Breakdown by industry sector for diversity analysis | Shannon entropy on sector distribution
A3: S.No. | B3: University Name | C3: Country | D3: IT/Software | E3: Pharma/Biotech | F3: Automotive/Mfg | G3: Energy/Oil&Gas | H3: FMCG/Consumer | I3: Defence/Aero | J3: Agri/Food | K3: Telecom | L3: Finance/Banking | M3: Construction/Infra | N3: Other | O3: Total (Auto-Sum) | P3: Sector Entropy (H)
A4: 1 | O4: =SUM(D4:N4) -> 0 | P4: =IFERROR(IF(O4>0,-SUMPRODUCT(IF(D4:N4>0,(D4:N4/O4)*LOG(D4:N4/O4,2),0)),0),0) -> 0
A5: 2 | O5: =SUM(D5:N5) -> 0 | P5: =IFERROR(IF(O5>0,-SUMPRODUCT(IF(D5:N5>0,(D5:N5/O5)*LOG(D5:N5/O5,2),0)),0),0) -> 0
A6: 3 | O6: =SUM(D6:N6) -> 0 | P6: =IFERROR(IF(O6>0,-SUMPRODUCT(IF(D6:N6>0,(D6:N6/O6)*LOG(D6:N6/O6,2),0)),0),0) -> 0
A7: 4 | O7: =SUM(D7:N7) -> 0 | P7: =IFERROR(IF(O7>0,-SUMPRODUCT(IF(D7:N7>0,(D7:N7/O7)*LOG(D7:N7/O7,2),0)),0),0) -> 0
A8: 5 | O8: =SUM(D8:N8) -> 0 | P8: =IFERROR(IF(O8>0,-SUMPRODUCT(IF(D8:N8>0,(D8:N8/O8)*LOG(D8:N8/O8,2),0)),0),0) -> 0
A9: 6 | O9: =SUM(D9:N9) -> 0 | P9: =IFERROR(IF(O9>0,-SUMPRODUCT(IF(D9:N9>0,(D9:N9/O9)*LOG(D9:N9/O9,2),0)),0),0) -> 0
A10: 7 | O10: =SUM(D10:N10) -> 0 | P10: =IFERROR(IF(O10>0,-SUMPRODUCT(IF(D10:N10>0,(D10:N10/O10)*LOG(D10:N10/O10,2),0)),0),0) -> 0
A11: 8 | O11: =SUM(D11:N11) -> 0 | P11: =IFERROR(IF(O11>0,-SUMPRODUCT(IF(D11:N11>0,(D11:N11/O11)*LOG(D11:N11/O11,2),0)),0),0) -> 0
A12: 9 | O12: =SUM(D12:N12) -> 0 | P12: =IFERROR(IF(O12>0,-SUMPRODUCT(IF(D12:N12>0,(D12:N12/O12)*LOG(D12:N12/O12,2),0)),0),0) -> 0
A13: 10 | O13: =SUM(D13:N13) -> 0 | P13: =IFERROR(IF(O13>0,-SUMPRODUCT(IF(D13:N13>0,(D13:N13/O13)*LOG(D13:N13/O13,2),0)),0),0) -> 0
A14: 11 | O14: =SUM(D14:N14) -> 0 | P14: =IFERROR(IF(O14>0,-SUMPRODUCT(IF(D14:N14>0,(D14:N14/O14)*LOG(D14:N14/O14,2),0)),0),0) -> 0
A15: 12 | O15: =SUM(D15:N15) -> 0 | P15: =IFERROR(IF(O15>0,-SUMPRODUCT(IF(D15:N15>0,(D15:N15/O15)*LOG(D15:N15/O15,2),0)),0),0) -> 0
... A33: 30 | O33: =SUM(D33:N33) -> 0 | P33: =IFERROR(IF(O33>0,-SUMPRODUCT(IF(D33:N33>0,(D33:N33/O33)*LOG(D33:N33/O33,2),0)),0),0) -> 0

Sheet 3. Cross-Disc. Industry
A1: Cross-Disciplinary Industry Funding — Projects Spanning 2+ Departments
A2: Subset of industry income allocated to multi-domain projects | Co-funded labs, multi-dept sponsored research
A3: S.No. | B3: University Name | C3: Country | D3: Total Industry Funding (5yr) | E3: Co-Funded Joint Lab / Centre Funding | F3: Multi-Dept Sponsored Projects | G3: Industry Chairs (Cross-Domain) | H3: Total Cross-Disc. Industry Funding | I3: % Cross-Disciplinary | J3: Reporting Period
A4: 1 | H4: =SUM(E4:G4) -> 0 | I4: =IF(D4>0,H4/D4*100,0) -> 0
A5: 2 | H5: =SUM(E5:G5) -> 0 | I5: =IF(D5>0,H5/D5*100,0) -> 0
A6: 3 | H6: =SUM(E6:G6) -> 0 | I6: =IF(D6>0,H6/D6*100,0) -> 0
A7: 4 | H7: =SUM(E7:G7) -> 0 | I7: =IF(D7>0,H7/D7*100,0) -> 0
A8: 5 | H8: =SUM(E8:G8) -> 0 | I8: =IF(D8>0,H8/D8*100,0) -> 0
A9: 6 | H9: =SUM(E9:G9) -> 0 | I9: =IF(D9>0,H9/D9*100,0) -> 0
A10: 7 | H10: =SUM(E10:G10) -> 0 | I10: =IF(D10>0,H10/D10*100,0) -> 0
A11: 8 | H11: =SUM(E11:G11) -> 0 | I11: =IF(D11>0,H11/D11*100,0) -> 0
A12: 9 | H12: =SUM(E12:G12) -> 0 | I12: =IF(D12>0,H12/D12*100,0) -> 0
A13: 10 | H13: =SUM(E13:G13) -> 0 | I13: =IF(D13>0,H13/D13*100,0) -> 0
A14: 11 | H14: =SUM(E14:G14) -> 0 | I14: =IF(D14>0,H14/D14*100,0) -> 0
A15: 12 | H15: =SUM(E15:G15) -> 0 | I15: =IF(D15>0,H15/D15*100,0) -> 0
... A33: 30 | H33: =SUM(E33:G33) -> 0 | I33: =IF(D33>0,H33/D33*100,0) -> 0
A35: Detailed Cross-Disciplinary Industry Project Log
A36: S.No. | B36: Project Title | C36: Industry Partner | D36: Amount (INR L / USD K) | E36: Disciplines / ASJC Areas (2+) | F36: University Departments Involved | G36: PI & Co-PI | H36: Duration (Years) | I36: Status (Active/Completed) | J36: University Name
A37: 1
A38: 2
A39: 3
A40: 4
A41: 5
A42: 6
A43: 7
A44: 8
A45: 9
A46: 10
A47: 11
A48: 12
... A86: 50

Sheet 4. Partner Diversity
A1: Industry Partner Diversity — Breadth & Entropy of Partner Portfolio
A2: Shannon entropy on sector distribution | More diverse partners = stronger knowledge exchange capacity
A3: S.No. | B3: University Name | C3: Country | D3: Total Unique Industry Partners | E3: No. of Industry Sectors Represented | F3: Top Industry Partner (by funding) | G3: Top Industry Sector (by funding) | H3: Sector Entropy H (bits) | I3: Partner Diversity Score (0–100) | J3: Diversity Tier
A4: 1 | H4: ='2. Funding by Sector'!P4 -> 0 | I4: =IFERROR(IF(MAX($H$4:$H$33)>0,H4/MAX($H$4:$H$33)*100,0),0) -> 0 | J4: =IF(I4>=80,"Very High",IF(I4>=60,"High",IF(I4>=40,"Medium",IF(I4>=20,"Low","Very Low")))) -> Very Low
A5: 2 | H5: ='2. Funding by Sector'!P5 -> 0 | I5: =IFERROR(IF(MAX($H$4:$H$33)>0,H5/MAX($H$4:$H$33)*100,0),0) -> 0 | J5: =IF(I5>=80,"Very High",IF(I5>=60,"High",IF(I5>=40,"Medium",IF(I5>=20,"Low","Very Low")))) -> Very Low
A6: 3 | H6: ='2. Funding by Sector'!P6 -> 0 | I6: =IFERROR(IF(MAX($H$4:$H$33)>0,H6/MAX($H$4:$H$33)*100,0),0) -> 0 | J6: =IF(I6>=80,"Very High",IF(I6>=60,"High",IF(I6>=40,"Medium",IF(I6>=20,"Low","Very Low")))) -> Very Low
A7: 4 | H7: ='2. Funding by Sector'!P7 -> 0 | I7: =IFERROR(IF(MAX($H$4:$H$33)>0,H7/MAX($H$4:$H$33)*100,0),0) -> 0 | J7: =IF(I7>=80,"Very High",IF(I7>=60,"High",IF(I7>=40,"Medium",IF(I7>=20,"Low","Very Low")))) -> Very Low
A8: 5 | H8: ='2. Funding by Sector'!P8 -> 0 | I8: =IFERROR(IF(MAX($H$4:$H$33)>0,H8/MAX($H$4:$H$33)*100,0),0) -> 0 | J8: =IF(I8>=80,"Very High",IF(I8>=60,"High",IF(I8>=40,"Medium",IF(I8>=20,"Low","Very Low")))) -> Very Low
A9: 6 | H9: ='2. Funding by Sector'!P9 -> 0 | I9: =IFERROR(IF(MAX($H$4:$H$33)>0,H9/MAX($H$4:$H$33)*100,0),0) -> 0 | J9: =IF(I9>=80,"Very High",IF(I9>=60,"High",IF(I9>=40,"Medium",IF(I9>=20,"Low","Very Low")))) -> Very Low
A10: 7 | H10: ='2. Funding by Sector'!P10 -> 0 | I10: =IFERROR(IF(MAX($H$4:$H$33)>0,H10/MAX($H$4:$H$33)*100,0),0) -> 0 | J10: =IF(I10>=80,"Very High",IF(I10>=60,"High",IF(I10>=40,"Medium",IF(I10>=20,"Low","Very Low")))) -> Very Low
A11: 8 | H11: ='2. Funding by Sector'!P11 -> 0 | I11: =IFERROR(IF(MAX($H$4:$H$33)>0,H11/MAX($H$4:$H$33)*100,0),0) -> 0 | J11: =IF(I11>=80,"Very High",IF(I11>=60,"High",IF(I11>=40,"Medium",IF(I11>=20,"Low","Very Low")))) -> Very Low
A12: 9 | H12: ='2. Funding by Sector'!P12 -> 0 | I12: =IFERROR(IF(MAX($H$4:$H$33)>0,H12/MAX($H$4:$H$33)*100,0),0) -> 0 | J12: =IF(I12>=80,"Very High",IF(I12>=60,"High",IF(I12>=40,"Medium",IF(I12>=20,"Low","Very Low")))) -> Very Low
A13: 10 | H13: ='2. Funding by Sector'!P13 -> 0 | I13: =IFERROR(IF(MAX($H$4:$H$33)>0,H13/MAX($H$4:$H$33)*100,0),0) -> 0 | J13: =IF(I13>=80,"Very High",IF(I13>=60,"High",IF(I13>=40,"Medium",IF(I13>=20,"Low","Very Low")))) -> Very Low
A14: 11 | H14: ='2. Funding by Sector'!P14 -> 0 | I14: =IFERROR(IF(MAX($H$4:$H$33)>0,H14/MAX($H$4:$H$33)*100,0),0) -> 0 | J14: =IF(I14>=80,"Very High",IF(I14>=60,"High",IF(I14>=40,"Medium",IF(I14>=20,"Low","Very Low")))) -> Very Low
A15: 12 | H15: ='2. Funding by Sector'!P15 -> 0 | I15: =IFERROR(IF(MAX($H$4:$H$33)>0,H15/MAX($H$4:$H$33)*100,0),0) -> 0 | J15: =IF(I15>=80,"Very High",IF(I15>=60,"High",IF(I15>=40,"Medium",IF(I15>=20,"Low","Very Low")))) -> Very Low
... A33: 30 | H33: ='2. Funding by Sector'!P33 -> 0 | I33: =IFERROR(IF(MAX($H$4:$H$33)>0,H33/MAX($H$4:$H$33)*100,0),0) -> 0 | J33: =IF(I33>=80,"Very High",IF(I33>=60,"High",IF(I33>=40,"Medium",IF(I33>=20,"Low","Very Low")))) -> Very Low

Sheet 5. Joint Centres & Chairs
A1: Industry Co-Funded R&D Centres, Endowed Chairs & Joint Laboratories
A2: Formally established industry-university joint infrastructure | Per-unit detail
A3: S.No. | B3: Centre / Chair / Lab Name | C3: Industry Partner(s) | D3: Disciplines Integrated (2+) | E3: Year Established | F3: Industry Funding (INR L / USD K) | G3: Faculty Attached | H3: Research Outputs (5yr) | I3: Active (Y/N) | J3: University Name
A4: 1
A5: 2
A6: 3
A7: 4
A8: 5
A9: 6
A10: 7
A11: 8
A12: 9
A13: 10
A14: 11
A15: 12
... A53: 50
A55: University-Level Summary — Joint Infrastructure
A56: S.No. | B56: University Name | C56: Total Joint Centres | D56: Total Endowed Chairs | E56: Total Co-Funded Labs | F56: Total Industry Investment | G56: Avg Disciplines per Unit | H56: Total Outputs from Joint Infra | I56: Active Rate (%) | J56: Reporting Year
A57: 1
A58: 2
A59: 3
A60: 4
A61: 5
A62: 6
A63: 7
A64: 8
A65: 9
A66: 10
A67: 11
A68: 12
... A76: 20

Sheet 6. Growth & Pipeline
A1: Industry Funding Sustainability, Growth & Pipeline
A2: CAGR | Multi-year vs one-off | Pipeline of signed but un-disbursed commitments
A3: S.No. | B3: University Name | C3: Country | D3: Year 1 Industry Funding | E3: Year 2 | F3: Year 3 | G3: Year 4 | H3: Year 5 | I3: CAGR (%) | J3: Pipeline Value (Signed, Un-disbursed) | K3: % Multi-Year Agreements
A4: 1 | I4: =IFERROR(IF(AND(D4>0,H4>0),(H4/D4)^(1/4)-1,0)*100,0) -> 0
A5: 2 | I5: =IFERROR(IF(AND(D5>0,H5>0),(H5/D5)^(1/4)-1,0)*100,0) -> 0
A6: 3 | I6: =IFERROR(IF(AND(D6>0,H6>0),(H6/D6)^(1/4)-1,0)*100,0) -> 0
A7: 4 | I7: =IFERROR(IF(AND(D7>0,H7>0),(H7/D7)^(1/4)-1,0)*100,0) -> 0
A8: 5 | I8: =IFERROR(IF(AND(D8>0,H8>0),(H8/D8)^(1/4)-1,0)*100,0) -> 0
A9: 6 | I9: =IFERROR(IF(AND(D9>0,H9>0),(H9/D9)^(1/4)-1,0)*100,0) -> 0
A10: 7 | I10: =IFERROR(IF(AND(D10>0,H10>0),(H10/D10)^(1/4)-1,0)*100,0) -> 0
A11: 8 | I11: =IFERROR(IF(AND(D11>0,H11>0),(H11/D11)^(1/4)-1,0)*100,0) -> 0
A12: 9 | I12: =IFERROR(IF(AND(D12>0,H12>0),(H12/D12)^(1/4)-1,0)*100,0) -> 0
A13: 10 | I13: =IFERROR(IF(AND(D13>0,H13>0),(H13/D13)^(1/4)-1,0)*100,0) -> 0
A14: 11 | I14: =IFERROR(IF(AND(D14>0,H14>0),(H14/D14)^(1/4)-1,0)*100,0) -> 0
A15: 12 | I15: =IFERROR(IF(AND(D15>0,H15>0),(H15/D15)^(1/4)-1,0)*100,0) -> 0
... A33: 30 | I33: =IFERROR(IF(AND(D33>0,H33>0),(H33/D33)^(1/4)-1,0)*100,0) -> 0

Sheet 7. Consultancy Income
A1: Industry Consultancy & Technical Service Income
A2: Revenue from consultancy, testing, certification using multi-domain expertise | Separate from sponsored R&D
A3: S.No. | B3: University Name | C3: Country | D3: Total Consultancy Income (5yr, INR Cr / USD M) | E3: Cross-Domain Consultancy Income | F3: % Cross-Domain Consultancy | G3: Academic Staff (FTE) | H3: Consultancy per FTE | I3: Reporting Period
A4: 1 | F4: =IF(D4>0,E4/D4*100,0) -> 0 | H4: =IF(G4>0,D4/G4,0) -> 0
A5: 2 | F5: =IF(D5>0,E5/D5*100,0) -> 0 | H5: =IF(G5>0,D5/G5,0) -> 0
A6: 3 | F6: =IF(D6>0,E6/D6*100,0) -> 0 | H6: =IF(G6>0,D6/G6,0) -> 0
A7: 4 | F7: =IF(D7>0,E7/D7*100,0) -> 0 | H7: =IF(G7>0,D7/G7,0) -> 0
A8: 5 | F8: =IF(D8>0,E8/D8*100,0) -> 0 | H8: =IF(G8>0,D8/G8,0) -> 0
A9: 6 | F9: =IF(D9>0,E9/D9*100,0) -> 0 | H9: =IF(G9>0,D9/G9,0) -> 0
A10: 7 | F10: =IF(D10>0,E10/D10*100,0) -> 0 | H10: =IF(G10>0,D10/G10,0) -> 0
A11: 8 | F11: =IF(D11>0,E11/D11*100,0) -> 0 | H11: =IF(G11>0,D11/G11,0) -> 0
A12: 9 | F12: =IF(D12>0,E12/D12*100,0) -> 0 | H12: =IF(G12>0,D12/G12,0) -> 0
A13: 10 | F13: =IF(D13>0,E13/D13*100,0) -> 0 | H13: =IF(G13>0,D13/G13,0) -> 0
A14: 11 | F14: =IF(D14>0,E14/D14*100,0) -> 0 | H14: =IF(G14>0,D14/G14,0) -> 0
A15: 12 | F15: =IF(D15>0,E15/D15*100,0) -> 0 | H15: =IF(G15>0,D15/G15,0) -> 0
... A33: 30 | F33: =IF(D33>0,E33/D33*100,0) -> 0 | H33: =IF(G33>0,D33/G33,0) -> 0
A35: Detailed Consultancy / Service Engagement Log
A36: S.No. | B36: Consultancy Title / Service | C36: Industry Client | D36: Amount (INR L / USD K) | E36: Domains Applied (2+) | F36: Departments Involved | G36: Faculty Lead | H36: Year | I36: University Name
A37: 1
A38: 2
A39: 3
A40: 4
A41: 5
A42: 6
A43: 7
A44: 8
A45: 9
A46: 10
A47: 11
A48: 12
... A76: 40

Sheet 8. Ecosystem Checklist
A1: Industry Engagement Ecosystem — Structural Readiness Checklist
A2: Institutional mechanisms enabling industry R&D funding | Per-university assessment
A3: # | B3: University Name | C3: Ecosystem Component | D3: Status (Y/N/Planned) | E3: Scale / Evidence | F3: Year Established | G3: Remarks
A4: 1 | C4: Dedicated Industry Liaison / Corporate Relations Office
A5: 2 | C5: Institutional IP policy incentivizing industry-funded research
A6: 3 | C6: Industry Advisory Board at university level (with cross-sector representation)
A7: 4 | C7: Standard MoU / agreement template for industry R&D partnerships
A8: 5 | C8: Streamlined approval process for industry-funded projects (<30 days)
A9: 6 | C9: Industry co-funded research chairs / professorships programme
A10: 7 | C10: Joint R&D centre framework (space, governance, IP sharing)
A11: 8 | C11: Industry sabbatical / visiting researcher programme
A12: 9 | C12: Faculty incentive structure rewarding industry-funded research output
A13: 10 | C13: Industry-sponsored PhD / postdoc fellowship programme
A14: 11 | C14: Shared prototyping / pilot-scale facility available to industry partners
A15: 12 | C15: Annual industry-academia conclave / research showcase event
... A21: 18 | C21: CSR-to-R&D conversion pipeline for industry CSR funds
A23: Ecosystem Summary
A24: Total Components Present | D24: =COUNTIF(D4:D21,"Y") -> 0
A25: Ecosystem Readiness (%) | D25: =IFERROR(COUNTIF(D4:D21,"Y")/18*100,0) -> 0

Sheet 9. Composite IF Score
A1: Composite Industry Funding Score (0–100) — 11% of Total Ranking
A2: Weighted composite of 6 sub-indicators | Weights editable in Row 4
A3: S.No. | B3: University Name | C3: Income/FTE (A) | D3: Cross-Disc. % (B) | E3: Partner Diversity (C) | F3: Joint Centres (D) | G3: Growth/Pipeline (E) | H3: Consultancy (F) | I3: Composite IF Score (0–100) | J3: Global Rank
B4: Weights → | C4: 0.3636 | D4: 0.2273 | E4: 0.1364 | F4: 0.1364 | G4: 0.0909 | H4: 0.0455
A5: 1 | I5: =C5*$C$4+D5*$D$4+E5*$E$4+F5*$F$4+G5*$G$4+H5*$H$4 -> 0 | J5: =IFERROR(RANK(I5,$I$5:$I$34,0),"") -> 1
A6: 2 | I6: =C6*$C$4+D6*$D$4+E6*$E$4+F6*$F$4+G6*$G$4+H6*$H$4 -> 0 | J6: =IFERROR(RANK(I6,$I$5:$I$34,0),"") -> 1
A7: 3 | I7: =C7*$C$4+D7*$D$4+E7*$E$4+F7*$F$4+G7*$G$4+H7*$H$4 -> 0 | J7: =IFERROR(RANK(I7,$I$5:$I$34,0),"") -> 1
A8: 4 | I8: =C8*$C$4+D8*$D$4+E8*$E$4+F8*$F$4+G8*$G$4+H8*$H$4 -> 0 | J8: =IFERROR(RANK(I8,$I$5:$I$34,0),"") -> 1
A9: 5 | I9: =C9*$C$4+D9*$D$4+E9*$E$4+F9*$F$4+G9*$G$4+H9*$H$4 -> 0 | J9: =IFERROR(RANK(I9,$I$5:$I$34,0),"") -> 1
A10: 6 | I10: =C10*$C$4+D10*$D$4+E10*$E$4+F10*$F$4+G10*$G$4+H10*$H$4 -> 0 | J10: =IFERROR(RANK(I10,$I$5:$I$34,0),"") -> 1
A11: 7 | I11: =C11*$C$4+D11*$D$4+E11*$E$4+F11*$F$4+G11*$G$4+H11*$H$4 -> 0 | J11: =IFERROR(RANK(I11,$I$5:$I$34,0),"") -> 1
A12: 8 | I12: =C12*$C$4+D12*$D$4+E12*$E$4+F12*$F$4+G12*$G$4+H12*$H$4 -> 0 | J12: =IFERROR(RANK(I12,$I$5:$I$34,0),"") -> 1
A13: 9 | I13: =C13*$C$4+D13*$D$4+E13*$E$4+F13*$F$4+G13*$G$4+H13*$H$4 -> 0 | J13: =IFERROR(RANK(I13,$I$5:$I$34,0),"") -> 1
A14: 10 | I14: =C14*$C$4+D14*$D$4+E14*$E$4+F14*$F$4+G14*$G$4+H14*$H$4 -> 0 | J14: =IFERROR(RANK(I14,$I$5:$I$34,0),"") -> 1
A15: 11 | I15: =C15*$C$4+D15*$D$4+E15*$E$4+F15*$F$4+G15*$G$4+H15*$H$4 -> 0 | J15: =IFERROR(RANK(I15,$I$5:$I$34,0),"") -> 1
A16: 12 | I16: =C16*$C$4+D16*$D$4+E16*$E$4+F16*$F$4+G16*$G$4+H16*$H$4 -> 0 | J16: =IFERROR(RANK(I16,$I$5:$I$34,0),"") -> 1
... A34: 30 | I34: =C34*$C$4+D34*$D$4+E34*$E$4+F34*$F$4+G34*$G$4+H34*$H$4 -> 0 | J34: =IFERROR(RANK(I34,$I$5:$I$34,0),"") -> 1

Sheet 10. Benchmarking
A1: Benchmarking & Peer Comparison — Industry Funding
A2: Compare against peers, aspirational targets, and global top performers
A3: S.No. | B3: University / Benchmark | C3: Income/FTE | D3: X-Disc % | E3: Diversity | F3: Centres | G3: Growth | H3: Consultancy | I3: Composite IF | J3: Peer Group
A4: 1 | B4: Your Institution | J4: Target
A5: 2 | B5: Global Top 10 Average | J5: Aspirational
A6: 3 | B6: National Average | J6: National
A7: 4 | B7: Peer Group Average | J7: Peer
A8: 1
A9: 2
A10: 3
A11: 4
A12: 5
A13: 6
A14: 7
A15: 8
A16: 9
A17: 10
A18: 11
A19: 12
... A22: 15

Sheet 11. Data Quality Audit
A1: Industry Funding — Data Quality & Audit Checklist
A2: Validation checks for all sub-indicators of the Industry Funding component (11% of total ranking)
A3: # | B3: Quality Check | C3: Description | D3: Status (✓/✗/IP) | E3: Date | F3: Reviewer
A4: 1 | B4: Industry income definition | C4: Only R&D income from industry included; tuition/fee income from corporate training excluded
A5: 2 | B5: Sponsored R&D vs. consultancy separation | C5: Sponsored research (new knowledge creation) separated from consultancy (applying existing knowledge)
A6: 3 | B6: PPP normalization | C6: All figures converted to USD using World Bank PPP rates for the relevant year
A7: 4 | B7: FTE definition consistency | C7: Academic FTE per THE guidelines; excludes admin/technical support staff
A8: 5 | B8: 5-year window alignment | C8: All 5 years cover same fiscal/calendar year definition consistently
A9: 6 | B9: Cross-disciplinary project verification | C9: Each project classified as 'cross-disciplinary' verified as spanning 2+ departments in signed agreement
A10: 7 | B10: Double-counting prevention | C10: Same funding not counted in multiple sub-categories or across sheets
A11: 8 | B11: Industry sector classification | C11: All partners mapped to exactly one of 11 standard sectors; no 'unclassified' entries
A12: 9 | B12: Entropy calculation validation | C12: Shannon entropy uses log₂; proportions sum to 100%; verified for 2–3 universities manually
A13: 10 | B13: Joint centre active status | C13: All centres/chairs/labs marked 'Active' have produced output or received funding in past 3 years
A14: 11 | B14: CAGR formula verification | C14: CAGR = (Year5/Year1)^(1/4) − 1; negative growth handled correctly; verified
A15: 12 | B15: Pipeline value documentation | C15: Pipeline = signed agreements with future disbursement dates; backed by signed MoUs
... A23: 20 | B23: Reproducibility test | C23: All calculations reproducible by independent analyst using this workbook and financial records
